tap_fabdb/__init__.py
tap_fabdb/streams.py
tap_fabdb/tap.py
tap_fabdb/tests/__init__.py
tap_fabdb/tests/test_core.py
tap_fabdb-0.0.2.dist-info/entry_points.txt
tap_fabdb-0.0.2.dist-info/LICENSE
tap_fabdb-0.0.2.dist-info/WHEEL
tap_fabdb-0.0.2.dist-info/METADATA
tap_fabdb-0.0.2.dist-info/RECORD
