Metadata-Version: 2.1
Name: tap-fabdb
Version: 0.0.2
Summary: A Singer tap for extracting data from the FaB DB API, built with the Singer SDK.
License: MIT
Keywords: flesh,and,blood
Author: David Wallace
Author-email: david.wallace@dutchie.com
Requires-Python: >=3.6.2,<3.10
Classifier: License :: OSI Approved :: MIT License
Classifier: Programming Language :: Python :: 3
Classifier: Programming Language :: Python :: 3.7
Classifier: Programming Language :: Python :: 3.8
Classifier: Programming Language :: Python :: 3.9
Requires-Dist: singer-sdk (>=0.3.6,<0.4.0)
